{
    "data": {
        "__type": {
            "name": "StaticParticipant",
            "description": "A static participant for a team",
            "fields": [
                {
                    "name": "_id",
                    "type": {
                        "name": null,
                        "kind": "NON_NULL",
                        "ofType": {
                            "name": "ID",
                            "kind": "SCALAR"
                        }
                    }
                },
                {
                    "name": "avatar",
                    "type": {
                        "name": null,
                        "kind": "NON_NULL",
                        "ofType": {
                            "name": "String",
                            "kind": "SCALAR"
                        }
                    }
                },
                {
                    "name": "bio",
                    "type": {
                        "name": "String",
                        "kind": "SCALAR",
                        "ofType": null
                    }
                },
                {
                    "name": "external_url",
                    "type": {
                        "name": "String",
                        "kind": "SCALAR",
                        "ofType": null
                    }
                },
                {
                    "name": "id",
                    "type": {
                        "name": null,
                        "kind": "NON_NULL",
                        "ofType": {
                            "name": "ID",
                            "kind": "SCALAR"
                        }
                    }
                },
                {
                    "name": "name",
                    "type": {
                        "name": null,
                        "kind": "NON_NULL",
                        "ofType": {
                            "name": "String",
                            "kind": "SCALAR"
                        }
                    }
                },
                {
                    "name": "year",
                    "type": {
                        "name": "String",
                        "kind": "SCALAR",
                        "ofType": null
                    }
                }
            ]
        }
    }
}